_GTW/FO.py
_GTW/File_Session.py
_GTW/LICENSE
_GTW/Memory_Session.py
_GTW/Notification.py
_GTW/README.rst
_GTW/Request_Data.py
_GTW/Session.py
_GTW/V5a.py
_GTW/VERSION.py
_GTW/__init__.py
_GTW/babel.cfg
_GTW/deploy.py
_GTW/expand_CSS.py
_GTW/jQuery.py
_GTW/setup.cfg
_GTW/setup.py
_GTW/-I18N/de-js.po
_GTW/-I18N/de.js
_GTW/-I18N/de.po
_GTW/-I18N/en.po
_GTW/-I18N/pt.po
_GTW/-I18N/template-js.pot
_GTW/-I18N/template.pot
_GTW/_MF3/Completer.py
_GTW/_MF3/Element.py
_GTW/_MF3/Error.py
_GTW/_MF3/Polisher.py
_GTW/_MF3/Submission.py
_GTW/_MF3/__init__.py
_GTW/_MF3/babel.cfg
_GTW/_MF3/-I18N/de.po
_GTW/_MF3/-I18N/en.po
_GTW/_MF3/-I18N/pt.po
_GTW/_MF3/-I18N/template.pot
_GTW/_OMP/Command.py
_GTW/_OMP/MOM_injector.py
_GTW/_OMP/__init__.py
_GTW/_OMP/deploy.py
_GTW/_OMP/_Auth/Account.py
_GTW/_OMP/_Auth/Account_Handling.py
_GTW/_OMP/_Auth/Account_in_Group.py
_GTW/_OMP/_Auth/Certificate.py
_GTW/_OMP/_Auth/Group.py
_GTW/_OMP/_Auth/UI_Spec.py
_GTW/_OMP/_Auth/__babel__.py
_GTW/_OMP/_Auth/__init__.py
_GTW/_OMP/_Auth/babel.cfg
_GTW/_OMP/_Auth/graph.py
_GTW/_OMP/_Auth/import_Auth.py
_GTW/_OMP/_Auth/-I18N/de.po
_GTW/_OMP/_Auth/-I18N/en.po
_GTW/_OMP/_Auth/-I18N/pt.po
_GTW/_OMP/_Auth/-I18N/template.pot
_GTW/_OMP/_DNS/AAAA_Record.py
_GTW/_OMP/_DNS/A_Record.py
_GTW/_OMP/_DNS/Attr_Type.py
_GTW/_OMP/_DNS/CNAME_Record.py
_GTW/_OMP/_DNS/MX_Record.py
_GTW/_OMP/_DNS/NS_Record.py
_GTW/_OMP/_DNS/Record.py
_GTW/_OMP/_DNS/SRV_Record.py
_GTW/_OMP/_DNS/Secondary.py
_GTW/_OMP/_DNS/Secondary_IP4.py
_GTW/_OMP/_DNS/Secondary_IP6.py
_GTW/_OMP/_DNS/TXT_Record.py
_GTW/_OMP/_DNS/UI_Spec.py
_GTW/_OMP/_DNS/Zone.py
_GTW/_OMP/_DNS/__init__.py
_GTW/_OMP/_DNS/import_DNS.py
_GTW/_OMP/_EVT/Calendar.py
_GTW/_OMP/_EVT/Event.py
_GTW/_OMP/_EVT/Recurrence_Spec.py
_GTW/_OMP/_EVT/UI_Spec.py
_GTW/_OMP/_EVT/__babel__.py
_GTW/_OMP/_EVT/__init__.py
_GTW/_OMP/_EVT/babel.cfg
_GTW/_OMP/_EVT/graph.py
_GTW/_OMP/_EVT/import_EVT.py
_GTW/_OMP/_EVT/-I18N/de.po
_GTW/_OMP/_EVT/-I18N/en.po
_GTW/_OMP/_EVT/-I18N/pt.po
GTW-3.9.dist-info/LICENSE
GTW-3.9.dist-info/METADATA
GTW-3.9.dist-info/WHEEL
GTW-3.9.dist-info/top_level.txt
GTW-3.9.dist-info/RECORD
